<AstroObjectEntry xmlns:xsi="http://www.w3.org/2001/XMLSchema-instance"
                  xsi:noNamespaceSchemaLocation="https://raw.githubusercontent.com/Outer-Wilds-New-Horizons/new-horizons/main/NewHorizons/Schemas/shiplog_schema.xsd">
  <ID>FRACTURED_HARMONY</ID>

  <Entry>
    <ID>BT_GREAT_DOOR</ID>
    <Name>The Great Door</Name>
    <Curiosity>BT_GREAT_DOOR</Curiosity>
    <IsCuriosity/>
    <IgnoreMoreToExplore/>

    <RumorFact>
      <ID>BT_PLANET_RUMOR</ID>
      <RumorName>Fractured Harmony</RumorName>
      <Text>A planet in the solar system. I hear a signal coming from somewhere on it.</Text>
    </RumorFact>

    <ExploreFact>
      <ID>BT_GREAT_DOOR_INIT</ID>
      <Text>A mysterious, large door. The Nomai says they haven't been able to open it for centuries.</Text>
    </ExploreFact>

    <ExploreFact>
      <ID>BT_GREAT_DOOR_CLANS_AGREED</ID>
      <Text>I convinced every clan to contribute their shard, but we're still missing one.</Text>
      <AltText>
        <Text>I convinced every clan to contribute their shard and found the final missing shard.</Text>
        <Condition>BT_FIFTH_SHARD_FOUND</Condition>
      </AltText>
    </ExploreFact>

    <ExploreFact>
      <ID>BT_KEY_COMPLETE</ID>
      <Text>When I put the last shard in, the door swung open.</Text>
    </ExploreFact>
  </Entry>
  
  <Entry>
    <ID>BT_NOMAI_VILLAGE_A</ID>
    <Name>The Followers of Greed</Name>
    <Curiosity>BT_GREAT_DOOR</Curiosity>

    <RumorFact>
      <ID>BT_NOMAI_VILLAGE_A_RUMOR</ID>
      <SourceID>BT_GREAT_DOOR</SourceID>
      <RumorName>Key Shard</RumorName>
      <Text>A Nomai told me that one of the shards was in a Nomai settlement on the north side of the planet.</Text>
    </RumorFact>

    <ExploreFact>
      <ID>BT_NOMAI_VILLAGE_A_FOUND</ID>
      <Text>I found a Nomai settlement on the north side of the planet. They call themselves the Followers of Greed.</Text>
    </ExploreFact>

    <ExploreFact>
      <ID>BT_NOMAI_VILLAGE_A_QUEST</ID>
      <Text>The Nomai told me that, to earn their trust, I have to prove my worth by stealing something from the Followers of Worship. They said that there wasn't anything good to steal right now.</Text>
      <AltText>
        <Text>The Nomai told me that, to earn their trust, I have to prove my worth by stealing something from the Followers of Worship.</Text>
        <Condition>BT_STEAL_QUEST</Condition>
      </AltText>
    </ExploreFact>

    <ExploreFact>
      <ID>BT_STEAL_QUEST</ID>
      <Text>The Nomai said I had to steal the Sacred Shrubbery from the Followers of Worship and bring It to them.</Text>
    </ExploreFact>

    <ExploreFact>
      <ID>BT_NOMAI_VILLAGE_A_AGREED</ID>
      <Text>The leader of the Followers of Greed agreed to help us open the Great Door by placing their shard into it.</Text>
    </ExploreFact>
  </Entry>

  <Entry>
    <ID>BT_NOMAI_VILLAGE_B</ID>
    <Name>The Followers of Exploration</Name>
    <Curiosity>BT_GREAT_DOOR</Curiosity>

    <RumorFact>
      <ID>BT_NOMAI_VILLAGE_B_RUMOR</ID>
      <SourceID>BT_GREAT_DOOR</SourceID>
      <RumorName>Key Shard</RumorName>
      <Text>A Nomai told me that one of the shards was in a Nomai settlement on the north side of the planet.</Text>
    </RumorFact>

    <ExploreFact>
      <ID>BT_NOMAI_VILLAGE_B_FOUND</ID>
      <Text>I found a Nomai settlement on the north side of the planet. They call themselves the Followers of Exploration.</Text>
    </ExploreFact>

    <ExploreFact>
      <ID>BT_NOMAI_VILLAGE_B_QUEST</ID>
      <Text>A Nomai told me I had to give them a cockpit to see their leader.</Text>
    </ExploreFact>

    <ExploreFact>
      <ID>BT_NOMAI_VILLAGE_B_AGREED</ID>
      <Text>The leader of the Followers of Exploration agreed to help us open the Great Door by placing their shard into it.</Text>
    </ExploreFact>
  </Entry>

  <Entry>
    <ID>BT_GHIRD_VILLAGE_B</ID>
    <Name>The Followers of Worship</Name>
    <Curiosity>BT_GREAT_DOOR</Curiosity>
    <AltPhotoCondition>BT_GHIRD_VILLAGE_B_FOUND</AltPhotoCondition>

    <RumorFact>
      <ID>BT_GHIRD_VILLAGE_B_RUMOR</ID>
      <SourceID>BT_GREAT_DOOR</SourceID>
      <RumorName>Key Shard</RumorName>
      <Text>A Nomai told me that one of the shards was in a Ghird village on the south side of the planet.</Text>
    </RumorFact>

    <ExploreFact>
      <ID>BT_GHIRD_VILLAGE_B_ELEVATOR</ID>
      <Text>I found a strange house that belongs to the Followers of Worship. The door leading inside is locked.</Text>
    </ExploreFact>

    <ExploreFact>
      <ID>BT_GHIRD_VILLAGE_B_ENTER</ID>
      <Text>I found a message written by a Nomai. It says the door to the house only opens when you don't have technology with you.</Text>
    </ExploreFact>

    <ExploreFact>
      <ID>BT_GHIRD_VILLAGE_B_FOUND</ID>
      <Text>I found a large underground shrine where the Followers of Worship are living.</Text>
    </ExploreFact>

    <ExploreFact>
      <ID>BT_GHIRD_VILLAGE_B_QUEST</ID>
      <Text>The leader of the Followers of Worship said that for them to help me I had to find the Sacred Shrubbery. They said It was on one of the islands next to theirs, but they weren't sure which one it was.</Text>
    </ExploreFact>

    <ExploreFact>
      <ID>BT_GHIRD_VILLAGE_B_AGREED</ID>
      <Text>The leader of the Followers of Worship said they would help us, but they sounded a little suspicious.</Text>
    </ExploreFact>

    <ExploreFact>
      <ID>BT_GHIRD_VILLAGE_B_AGREED_AGAIN</ID>
      <Text>After their Sacred Shrubbery mysteriously disappeared again, they decided to help us by placing their shard into the Great Door.</Text>
    </ExploreFact>
  </Entry>

  <Entry>
    <ID>BT_GHIRD_VILLAGE_A</ID>
    <Name>The Followers of Logic</Name>
    <Curiosity>BT_GREAT_DOOR</Curiosity>

    <RumorFact>
      <ID>BT_GHIRD_VILLAGE_A_RUMOR</ID>
      <SourceID>BT_GREAT_DOOR</SourceID>
      <RumorName>Key Shard</RumorName>
      <Text>A Nomai told me that one of the shards was in a Ghird village on the south side of the planet.</Text>
    </RumorFact>

    <ExploreFact>
      <ID>BT_GHIRD_VILLAGE_A_FOUND</ID>
      <Text>I found a Ghird village on the south side of the planet. They call themselves the Followers of Logic.</Text>
    </ExploreFact>

    <ExploreFact>
      <ID>BT_GHIRD_VILLAGE_A_AGREED</ID>
      <Text>The leader of the Followers of Logic agreed to help us open the Great Door by placing their shard into it.</Text>
    </ExploreFact>
    
    <Entry>
      <ID>BT_GHIRD_VILLAGE_A_PUZZLE</ID>
      <Name>Sunpost Code</Name>
      <Curiosity>BT_GREAT_DOOR</Curiosity>

      <RumorFact>
        <ID>BT_GHIRD_VILLAGE_A_PUZZLE_CODE</ID>
        <SourceID>BT_GHIRD_VILLAGE_A</SourceID>
        <RumorName>Secret Code</RumorName>
        <Text>I need a secret code to enter one of the houses.</Text>
      </RumorFact>

      <RumorFact>
        <ID>BT_GHIRD_VILLAGE_A_PUZZLE_SHADOW</ID>
        <SourceID>BT_NOMAI_VILLAGE_A</SourceID>
        <RumorName>Secret Code</RumorName>
        <Text>There is a secret code at one of the Ghird villages that uses shadows in some way.</Text>
        <AltText>
          <Text>The code uses shadows in some way.</Text>
          <Condition>BT_GHIRD_VILLAGE_A_PUZZLE_CODE</Condition>
        </AltText>
      </RumorFact>

      <RumorFact>
        <ID>BT_GHIRD_VILLAGE_A_PUZZLE_POST</ID>
        <SourceID>BT_GHIRD_VILLAGE_A</SourceID>
        <RumorName>Secret Code</RumorName>
        <Text>The code has something to do with the strange post on the island next to the village.</Text>
      </RumorFact>

      <RumorFact>
        <ID>BT_GHIRD_VILLAGE_A_PUZZLE_GEM</ID>
        <RumorName>Secret Code</RumorName>
        <Text>I saw a strange gem on the wall behind the Ghird. The Ghird said it glows when it's time to pray.</Text>
      </RumorFact>

      <ExploreFact>
        <ID>BT_GHIRD_VILLAGE_A_PUZZLE_SOLVED</ID>
        <Text>I solved the code by waiting until the shadow of the strange post was on the side of the building I wanted to enter.</Text>
      </ExploreFact>
    </Entry>
  </Entry>

  <Entry>
    <ID>BT_FIFTH_SHARD</ID>
    <Name>The Fifth Shard</Name>
    <Curiosity>BT_GREAT_DOOR</Curiosity>

    <RumorFact>
      <ID>BT_FIFTH_SHARD_RUMOR</ID>
      <RumorName>Fifth shard?</RumorName>
      <Text>The Nomai at the Great Door told me there was a fifth shard of the key that went missing.</Text>
    </RumorFact>

    <RumorFact>
      <ID>BT_FIFTH_SHARD_POS</ID>
      <SourceID>BT_NOMAI_VILLAGE_B</SourceID>
      <RumorName>Fifth shard?</RumorName>
      <Text>The leader of the Followers of Exploration told me: "Travel to the north pole..."</Text>
    </RumorFact>

    <RumorFact>
      <ID>BT_FIFTH_SHARD_QUANTUM</ID>
      <SourceID>BT_NOMAI_VILLAGE_A</SourceID>
      <RumorName>Fifth shard?</RumorName>
      <Text>The leader of the Followers of Greed told me: "Use the stone tainted with blood..."</Text>
    </RumorFact>

    <RumorFact>
      <ID>BT_FIFTH_SHARD_PILLAR</ID>
      <SourceID>BT_GHIRD_VILLAGE_B</SourceID>
      <RumorName>Fifth shard?</RumorName>
      <Text>The leader of the Followers of Worship told me: "Move it to the shortest pillar..."</Text>
    </RumorFact>

    <RumorFact>
      <ID>BT_FIFTH_SHARD_LIGHT</ID>
      <SourceID>BT_GHIRD_VILLAGE_A</SourceID>
      <RumorName>Fifth shard?</RumorName>
      <Text>The leader of the Followers of Logic told me: "Attach a light to the stone..."</Text>
    </RumorFact>

    <RumorFact>
      <ID>BT_FIFTH_SHARD_ACCIDENT</ID>
      <RumorName>The Fifth Shard</RumorName>
      <RumorNamePriority>2</RumorNamePriority>
      <Text>I found the Fifth Shard, but I'm not sure how I did it.</Text>
    </RumorFact>

    <ExploreFact>
      <ID>BT_FIFTH_SHARD_FOUND</ID>
      <Text>The final piece of the key to the Great Door. I found it on the North Pole locked behind a puzzle with quantum rocks.</Text>
    </ExploreFact>
  </Entry>

  <Entry>
    <ID>BT_ERNESTO</ID>
    <Name>Ernesto</Name>
    <Curiosity>BT_GREAT_DOOR</Curiosity>

    <RumorFact>
      <ID>BT_ERNESTO_RUMOR</ID>
      <RumorName>Ernesto?</RumorName>
      <Text>A Ghird from the Followers of Logic lost someone named Ernesto. They said that they had taken Ernesto to the South Pole to explore, and last saw him playing on a strange white rock. When the Ghird looked away to check their map, Ernesto mysteriously disappeared. The part about the map was strangely emphasized.</Text>
    </RumorFact>

    <ExploreFact>
      <ID>BT_ERNESTO_FOUND</ID>
      <Text>I found Ernesto by traveling with the white quantum rock to a strange underground house. I had to open my map so that I wasn't observing my surroundings.</Text>
    </ExploreFact>
  </Entry>
</AstroObjectEntry>